Metadata-Version: 2.1
Name: ix-pu-utils
Version: 0.1.1
Summary: Random stuff to help writing Pulumi scripts easier
Author-Email: injuryex <injuryex@ptnglobalcorp.com>
License:                                  Apache License
Project-URL: Source, https://github.com/ptnglobalcorp/pu-utils
Requires-Python: >=3.12.0
Requires-Dist: pulumi
Requires-Dist: uv
Requires-Dist: pyright; extra == "dev"
Requires-Dist: ruff; extra == "dev"
Requires-Dist: ward; extra == "dev"
Requires-Dist: twine; extra == "dev"
Requires-Dist: build; extra == "dev"
Requires-Dist: pulumi-aws; extra == "aws"
Provides-Extra: dev
Provides-Extra: aws
